{
  "": "",
  "Decrement": "Decrement",
  "Increment": "Increment",
  "Loading": "Loading",
  "Lorem ipsum dolor sit amet": "Lorem ipsum dolor sit amet",
  "Lorem ipsum dolor sit amet Lorem ipsum dolor sit amet": "Lorem ipsum dolor sit amet Lorem ipsum dolor sit amet",
  "Lorem ipsum dolor sit amet, consectetur adipisicing elit": {
    " Accusamus animi enim, eum explicabo harum labore odit! Aliquid illum unde veniam!": " Accusamus animi enim, eum explicabo harum labore odit! Aliquid illum unde veniam!"
  },
  "Profile page": "Profile page",
  "profile": {
    "Произошла ошибка при загрузке пользователя": "Произошла ошибка при загрузке пользователя"
  },
  "translation": {
    "Сохранить": "Сохранить"
  },
  "Айти": "Айти",
  "Валюта": "Валюта",
  "Ваш username": "Ваш username",
  "Ваш аватар": "Ваш аватар",
  "Ваш возраст": "Ваш возраст",
  "Ваш город": "Ваш город",
  "Ваша фамилия": "Ваша фамилия",
  "Ваше имя": "Ваше имя",
  "Введите имя пользователя": "Введите имя пользователя",
  "Введите пароль": "Введите пароль",
  "Войти": "Войти",
  "Все статьи": "Все статьи",
  "Вы ввели неверный логин или пароль": "Вы ввели неверный логин или пароль",
  "Выбранная валюта": "Выбранная валюта",
  "Выйти": "Выйти",
  "Главная": "Главная",
  "Главная страниц": "Главная страниц",
  "Главная страница": "Главная страница",
  "Главная страница ghjghj": "Главная страница ghjghj",
  "Главная страница23": "Главная страница23",
  "Город": "Город",
  "Данные не указаны": "Данные не указаны",
  "Дата создания": "Дата создания",
  "Добавить комментарий": "Добавить комментарий",
  "Заголовок": "Заголовок",
  "Имя и фамилия обязательны": "Имя и фамилия обязательны",
  "Имя пользователя": "Имя пользователя",
  "Искать статью": "Искать статью",
  "К списку статей": "К списку статей",
  "Комментарии": "Комментарии",
  "Копировать": "Копировать",
  "Лэйбл": "Лэйбл",
  "Люди": "Люди",
  "Модалка": "Модалка",
  "Назад к списку": "Назад к списку",
  "Название": "Название",
  "Наука": "Наука",
  "Некорректный возраст": "Некорректный возраст",
  "Некорректный регион": "Некорректный регион",
  "Новости": "Новости",
  "О сайте": "О сайте",
  "Обновить страницу": "Обновить страницу",
  "Отменить": "Отменить",
  "Отменить редактирование": "Отменить редактирование",
  "Отправить": "Отправить",
  "Ошибка_при_загрузке_пользователя": "Ошибка_при_загрузке_пользователя",
  "Пароль": "Пароль",
  "Перевести": "Перевести",
  "Переключить тему": "Переключить тему",
  "Персоны": "Персоны",
  "Плейсхолдер": "Плейсхолдер",
  "По возрастанию": "По возрастанию",
  "По убыванию": "По убыванию",
  "Поиск": "Поиск",
  "Поиск по статьям": "Поиск по статьям",
  "Пока нет комментариев": "Пока нет комментариев",
  "Попробуйте изменить параметры поиска": "Попробуйте изменить параметры поиска",
  "Попробуйте обновить страницу": "Попробуйте обновить страницу",
  "Попробуйте_обновить_страницу": "Попробуйте_обновить_страницу",
  "Порядок": "Порядок",
  "Порядок сортировки": "Порядок сортировки",
  "Произошла ошибка при загрузке пользователя": "Произошла ошибка при загрузке пользователя",
  "Произошла ошибка при загрузке статьи": "Произошла ошибка при загрузке статьи",
  "Просмотры": "Просмотры",
  "Профиль": "Профиль",
  "Редактировать": "Редактировать",
  "Рекомендуем": "Рекомендуем",
  "Серверная ошибка при сохранении": "Серверная ошибка при сохранении",
  "Сменить тему": "Сменить тему",
  "Сортировать по": "Сортировать по",
  "Сохранить": "Сохранить",
  "Ссылка на аватар": "Ссылка на аватар",
  "Статьи": "Статьи",
  "Статьи не найдены": "Статьи не найдены",
  "Статья не найдена": "Статья не найдена",
  "Страна": "Страна",
  "Страница не найдена": "Страница не найдена",
  "Ура!": "Ура!",
  "Форма авторизации": "Форма авторизации",
  "Что-то пошло не так": "Что-то пошло не так",
  "Экономика": "Экономика",
  "возрастанию": "возрастанию",
  "дате создания": "дате создания",
  "названию": "названию",
  "по": "по",
  "по возрастанию": "по возрастанию",
  "по убыванию": "по убыванию",
  "популярности": "популярности",
  "убыванию": "убыванию"
}
